rdbex/RdbEX.py
rdbex/__init__.py
rdbex/__internal/_func.py
rdbex/__internal/_recovery.py
rdbex/__internal/_var.py
rdbex/__internal/logs/don't fence me in.txt
rdbex/recovery.py
rdbex/utils.py
rdbex-0.2.6.dist-info/METADATA
rdbex-0.2.6.dist-info/WHEEL
rdbex-0.2.6.dist-info/RECORD
