Metadata-Version: 2.1
Name: rdbex
Version: 0.2.6
Summary: Replit DataBase EXtended
Author: Kokonico
Author-email: kokonico@duck.com
Requires-Python: >=3.9
Classifier: Programming Language :: Python :: 3
Classifier: Programming Language :: Python :: 3.9
Classifier: Programming Language :: Python :: 3.10
Classifier: Programming Language :: Python :: 3.11
Requires-Dist: packaging (>=23.2,<24.0)
Requires-Dist: replit (>=3.3.2,<4.0.0)
